LICENSE.txt
MANIFEST.in
README.rst
setup.py
neotime/__init__.py
neotime/__main__.py
neotime/arithmetic.py
neotime/clock_implementations.py
neotime/meta.py
neotime/metaclasses.py
neotime.egg-info/PKG-INFO
neotime.egg-info/SOURCES.txt
neotime.egg-info/dependency_links.txt
neotime.egg-info/requires.txt
neotime.egg-info/top_level.txt