Metadata-Version: 1.1
Name: neotime
Version: 1.7.1
Summary: Nanosecond resolution temporal types
Home-page: https://neotime.readthedocs.io
Author: Neo4j Drivers Team
Author-email: drivers@neo4j.com
License: Apache License, Version 2.0
Platform: UNKNOWN
Classifier: Intended Audience :: Developers
Classifier: License :: OSI Approved :: Apache Software License
Classifier: Operating System :: OS Independent
Classifier: Topic :: Software Development :: Libraries
Classifier: Programming Language :: Python :: 2.7
Classifier: Programming Language :: Python :: 3.4
Classifier: Programming Language :: Python :: 3.5
Classifier: Programming Language :: Python :: 3.6
Classifier: Programming Language :: Python :: 3.7
